aiojsonrpc2/__init__.py
aiojsonrpc2/connection.py
aiojsonrpc2/errors.py
aiojsonrpc2/protocols.py
aiojsonrpc2-1.0.0.dist-info/DESCRIPTION.rst
aiojsonrpc2-1.0.0.dist-info/METADATA
aiojsonrpc2-1.0.0.dist-info/RECORD
aiojsonrpc2-1.0.0.dist-info/WHEEL
aiojsonrpc2-1.0.0.dist-info/metadata.json
aiojsonrpc2-1.0.0.dist-info/top_level.txt
