Metadata-Version: 2.0
Name: aiojsonrpc2
Version: 1.0.0
Summary: Python3 asyncio JSONRPC module
Home-page: https://github.com/wetblanketcc/aiojsonrpc2
Author: wetblanketcc
Author-email: 35851045+wetblanketcc@users.noreply.github.com
License: MIT
Keywords: jsonrpc async asyncio aio json rpc
Platform: UNKNOWN
Classifier: Development Status :: 4 - Beta
Classifier: Environment :: Web Environment
Classifier: Framework :: AsyncIO
Classifier: Intended Audience :: Developers
Classifier: License :: OSI Approved :: MIT License
Classifier: Topic :: System :: Networking
Classifier: Programming Language :: Python :: 3
Classifier: Programming Language :: Python :: 3.5
Classifier: Programming Language :: Python :: 3.6
Requires-Python: >=3.5
